{
  "data": {
    "Default%": [
      0,
      0,
      0
    ],
    "MasterFile": "Metadata/Terrain/EndGame/MapDefiledCathedral/master.tsi"
  },
  "edge_count": 13,
  "edge_types": {
    "Metadata/Terrain/Dungeon/rooms.et": {
      "color": "#FF5A5A5A",
      "id": "rooms"
    },
    "Metadata/Terrain/Tools/void.et": {
      "color": "#FF141414",
      "id": "void"
    }
  },
  "edges": [
    {
      "color": "#FF5A5A5A",
      "edge_type": "Metadata/Terrain/Dungeon/rooms.et",
      "from": 11,
      "path": [],
      "to": 2,
      "unknown": [
        100,
        0,
        "Metadata/Terrain/Dungeon/rooms.et",
        0,
        0,
        "",
        0,
        0,
        0,
        "P",
        "N",
        1
      ]
    },
    {
      "color": "#FF5A5A5A",
      "edge_type": "Metadata/Terrain/Dungeon/rooms.et",
      "from": 8,
      "path": [],
      "to": 0,
      "unknown": [
        100,
        0,
        "Metadata/Terrain/Dungeon/rooms.et",
        0,
        0,
        "",
        0,
        0,
        0,
        "P",
        "N",
        1
      ]
    },
    {
      "color": "#FF5A5A5A",
      "edge_type": "Metadata/Terrain/Dungeon/rooms.et",
      "from": 14,
      "path": [],
      "to": 3,
      "unknown": [
        100,
        0,
        "Metadata/Terrain/Dungeon/rooms.et",
        0,
        0,
        "",
        0,
        0,
        0,
        "P",
        "N",
        1
      ]
    },
    {
      "color": "#FF5A5A5A",
      "edge_type": "Metadata/Terrain/Dungeon/rooms.et",
      "from": 10,
      "path": [],
      "to": 4,
      "unknown": [
        100,
        0,
        "Metadata/Terrain/Dungeon/rooms.et",
        0,
        0,
        "",
        0,
        0,
        0,
        "P",
        "N",
        1
      ]
    },
    {
      "color": "#FF141414",
      "edge_type": "Metadata/Terrain/Tools/void.et",
      "from": 5,
      "path": [],
      "to": 6,
      "unknown": [
        100,
        0,
        "Metadata/Terrain/Tools/void.et",
        0,
        0,
        "",
        0,
        0,
        0,
        "P",
        "V",
        1
      ]
    },
    {
      "color": "#FF5A5A5A",
      "edge_type": "Metadata/Terrain/Dungeon/rooms.et",
      "from": 2,
      "path": [],
      "to": 7,
      "unknown": [
        100,
        0,
        "Metadata/Terrain/Dungeon/rooms.et",
        0,
        0,
        "",
        0,
        0,
        0,
        "P",
        "N",
        1
      ]
    },
    {
      "color": "#FF5A5A5A",
      "edge_type": "Metadata/Terrain/Dungeon/rooms.et",
      "from": 7,
      "path": [],
      "to": 8,
      "unknown": [
        100,
        0,
        "Metadata/Terrain/Dungeon/rooms.et",
        0,
        0,
        "",
        0,
        0,
        0,
        "P",
        "N",
        1
      ]
    },
    {
      "color": "#FF5A5A5A",
      "edge_type": "Metadata/Terrain/Dungeon/rooms.et",
      "from": 0,
      "path": [],
      "to": 9,
      "unknown": [
        100,
        0,
        "Metadata/Terrain/Dungeon/rooms.et",
        0,
        0,
        "",
        0,
        0,
        0,
        "P",
        "N",
        1
      ]
    },
    {
      "color": "#FF5A5A5A",
      "edge_type": "Metadata/Terrain/Dungeon/rooms.et",
      "from": 9,
      "path": [],
      "to": 10,
      "unknown": [
        100,
        0,
        "Metadata/Terrain/Dungeon/rooms.et",
        0,
        0,
        "",
        0,
        0,
        0,
        "P",
        "N",
        1
      ]
    },
    {
      "color": "#FF5A5A5A",
      "edge_type": "Metadata/Terrain/Dungeon/rooms.et",
      "from": 3,
      "path": [],
      "to": 11,
      "unknown": [
        100,
        0,
        "Metadata/Terrain/Dungeon/rooms.et",
        0,
        0,
        "",
        0,
        0,
        0,
        "P",
        "N",
        1
      ]
    },
    {
      "color": "#FF141414",
      "edge_type": "Metadata/Terrain/Tools/void.et",
      "from": 12,
      "path": [],
      "to": 13,
      "unknown": [
        100,
        0,
        "Metadata/Terrain/Tools/void.et",
        0,
        0,
        "",
        0,
        0,
        0,
        "P",
        "V",
        1
      ]
    },
    {
      "color": "#FF5A5A5A",
      "edge_type": "Metadata/Terrain/Dungeon/rooms.et",
      "from": 15,
      "path": [],
      "to": 14,
      "unknown": [
        100,
        0,
        "Metadata/Terrain/Dungeon/rooms.et",
        0,
        0,
        "",
        0,
        0,
        0,
        "P",
        "N",
        1
      ]
    },
    {
      "color": "#FF5A5A5A",
      "edge_type": "Metadata/Terrain/Dungeon/rooms.et",
      "from": 4,
      "path": [],
      "to": 15,
      "unknown": [
        100,
        0,
        "Metadata/Terrain/Dungeon/rooms.et",
        0,
        0,
        "",
        0,
        0,
        0,
        "P",
        "N",
        1
      ]
    }
  ],
  "fill_tiles": [
    {
      "file": "default"
    },
    {
      "file": "Metadata/Terrain/Blank.tdt",
      "prefix": [
        "1"
      ]
    },
    {
      "file": "BlackInsideWall"
    },
    {
      "file": "Metadata/Terrain/Dungeon/black.tdt",
      "prefix": [
        "100"
      ]
    }
  ],
  "master": {
    "ChestData": "chests.cht",
    "Critters": "critters.clt",
    "Doodads": "doodads.ddt",
    "EdgeCombination": "combination.ecf",
    "Environment": "EndGameDefiledCathedral",
    "EnvironmentSector": "EndGameDefiledCathedral_boss\" \"boss_DefiledCathedral",
    "FillTiles": "random_fill_tiles.gft",
    "MaterialsList": "materials.mtd",
    "MixedMissions": null,
    "OuterBufferSize": null,
    "OuterGroundType": "Metadata/Terrain/black_inside_wall.gt",
    "RoomOverlap": null,
    "RoomSet": "generate.rs",
    "RoomUnitSize": null,
    "StoreyHeight": null,
    "TileSet": "tiles.tst",
    "version": null
  },
  "node_count": 16,
  "nodes": [
    {
      "numbers": [
        1,
        7
      ],
      "room": "entrance",
      "strings": [
        "default"
      ],
      "transform": "I",
      "unknown": [
        100,
        1,
        "N"
      ],
      "x": 78,
      "y": 195
    },
    {
      "numbers": [],
      "room": "boss",
      "strings": [
        "telepad2",
        "teleport1-%areaname%"
      ],
      "transform": "I",
      "unknown": [
        100,
        0,
        "N"
      ],
      "x": 79,
      "y": 8
    },
    {
      "numbers": [
        0,
        5
      ],
      "room": "stair",
      "strings": [],
      "transform": "R270",
      "unknown": [
        100,
        1,
        "N"
      ],
      "x": 14,
      "y": 143
    },
    {
      "numbers": [
        9,
        2
      ],
      "room": "boss_entry",
      "strings": [
        "telepad1",
        "teleport2-Arena"
      ],
      "transform": "R90",
      "unknown": [
        100,
        3,
        "N"
      ],
      "x": 79,
      "y": 124
    },
    {
      "numbers": [
        3,
        12
      ],
      "room": "stained",
      "strings": [],
      "transform": "R180",
      "unknown": [
        100,
        3,
        "N"
      ],
      "x": 189,
      "y": 106
    },
    {
      "numbers": [
        4
      ],
      "room": "",
      "strings": [],
      "transform": "(any)",
      "unknown": [
        100,
        0,
        "V"
      ],
      "x": 62,
      "y": 145
    },
    {
      "numbers": [
        4
      ],
      "room": "",
      "strings": [],
      "transform": "(any)",
      "unknown": [
        100,
        0,
        "V"
      ],
      "x": 95,
      "y": 144
    },
    {
      "numbers": [
        5,
        6
      ],
      "room": "stained",
      "strings": [],
      "transform": "I",
      "unknown": [
        100,
        1,
        "N"
      ],
      "x": 13,
      "y": 191
    },
    {
      "numbers": [
        6,
        1
      ],
      "room": "",
      "strings": [],
      "transform": "I",
      "unknown": [
        100,
        1,
        "N"
      ],
      "x": 38,
      "y": 193
    },
    {
      "numbers": [
        8,
        7
      ],
      "room": "",
      "strings": [],
      "transform": "FI",
      "unknown": [
        100,
        1,
        "N"
      ],
      "x": 119,
      "y": 194
    },
    {
      "numbers": [
        3,
        8
      ],
      "room": "stained_stairs",
      "strings": [],
      "transform": "I",
      "unknown": [
        100,
        1,
        "N"
      ],
      "x": 164,
      "y": 174
    },
    {
      "numbers": [
        9,
        0
      ],
      "room": "",
      "strings": [],
      "transform": "R180",
      "unknown": [
        100,
        3,
        "N"
      ],
      "x": 40,
      "y": 103
    },
    {
      "numbers": [
        10
      ],
      "room": "",
      "strings": [],
      "transform": "(any)",
      "unknown": [
        100,
        0,
        "V"
      ],
      "x": 13,
      "y": 80
    },
    {
      "numbers": [
        10
      ],
      "room": "",
      "strings": [],
      "transform": "(any)",
      "unknown": [
        100,
        0,
        "V"
      ],
      "x": 13,
      "y": 55
    },
    {
      "numbers": [
        11,
        2
      ],
      "room": "",
      "strings": [],
      "transform": "R180",
      "unknown": [
        100,
        3,
        "N"
      ],
      "x": 123,
      "y": 102
    },
    {
      "numbers": [
        11,
        12
      ],
      "room": "",
      "strings": [],
      "transform": "(any)",
      "unknown": [
        100,
        3,
        "N"
      ],
      "x": 168,
      "y": 125
    }
  ],
  "room_set": [
    {
      "file": "Metadata/Terrain/EndGame/MapDefiledCathedral/Rooms/Unique/defiled_boss.arm",
      "room_tag": "boss"
    },
    {
      "file": "Metadata/Terrain/EndGame/MapDefiledCathedral/Rooms/Unique/defiled_boss_entry.arm",
      "room_tag": "boss_entry"
    },
    {
      "file": "Metadata/Terrain/EndGame/MapDefiledCathedral/Rooms/Unique/defiled_entrance.arm",
      "room_tag": "entrance"
    },
    {
      "file": "Metadata/Terrain/EndGame/MapDefiledCathedral/Rooms/Unique/defiled_stained_corner_01.arm",
      "room_tag": "stained"
    },
    {
      "file": "Metadata/Terrain/EndGame/MapDefiledCathedral/Rooms/Unique/defiled_stained_corner_02.arm",
      "room_tag": "stained"
    },
    {
      "file": "Metadata/Terrain/EndGame/MapDefiledCathedral/Rooms/Unique/defiled_stained_straight_01.arm",
      "room_tag": "straight"
    },
    {
      "file": "Metadata/Terrain/EndGame/MapDefiledCathedral/Rooms/Unique/defiled_stained_straight_02.arm",
      "room_tag": "straight"
    },
    {
      "file": "Metadata/Terrain/EndGame/MapDefiledCathedral/Rooms/Unique/defiled_stained_straight_03.arm",
      "room_tag": "straight"
    },
    {
      "file": "Metadata/Terrain/EndGame/MapDefiledCathedral/Rooms/Unique/defiled_stained_straight_04.arm",
      "room_tag": "straight"
    },
    {
      "file": "Metadata/Terrain/EndGame/MapDefiledCathedral/Rooms/Unique/defiled_stained_straight_05.arm",
      "room_tag": "straight"
    },
    {
      "file": "Metadata/Terrain/EndGame/MapDefiledCathedral/Rooms/Unique/defiled_stained_straight_06.arm",
      "room_tag": "straight"
    },
    {
      "file": "Metadata/Terrain/EndGame/MapDefiledCathedral/Rooms/Unique/defiled_stained_straight_07.arm",
      "room_tag": "straight"
    },
    {
      "file": "Metadata/Terrain/EndGame/MapDefiledCathedral/Rooms/Unique/defiled_stained_straight_08.arm",
      "room_tag": "straight"
    },
    {
      "file": "Metadata/Terrain/EndGame/MapDefiledCathedral/Rooms/Unique/stained_stairs.arm",
      "room_tag": "stained_stairs"
    },
    {
      "file": "Metadata/Terrain/EndGame/MapDefiledCathedral/Rooms/Unique/stair.arm",
      "room_tag": "stair"
    },
    {
      "file": "Metadata/Terrain/EndGame/MapDefiledCathedral/Rooms/Unique/shrine_4.arm",
      "room_tag": "shrine"
    },
    {
      "file": "Metadata/Terrain/EndGame/MapDefiledCathedral/Rooms/Unique/shrine_2.arm",
      "room_tag": "shrine"
    },
    {
      "file": "Metadata/Terrain/EndGame/MapDefiledCathedral/Rooms/Unique/mission_4.arm",
      "room_tag": "mission"
    },
    {
      "file": "Metadata/Terrain/EndGame/MapDefiledCathedral/Rooms/Unique/Injectors/defiled_stained_straight_03_injector_5x5.arm",
      "room_tag": "room_injector5"
    },
    {
      "file": "Metadata/Terrain/EndGame/MapDefiledCathedral/Rooms/Unique/Injectors/defiled_stained_straight_03_injector_7x7.arm",
      "room_tag": "room_injector7"
    },
    {
      "file": "Metadata/Terrain/EndGame/MapDefiledCathedral/Rooms/Unique/Injectors/defiled_stained_straight_03_injector_9x9.arm",
      "room_tag": "room_injector9"
    },
    {
      "file": "Metadata/Terrain/EndGame/MapDefiledCathedral/Rooms/1x1/2_1.arm",
      "room_tag": ""
    },
    {
      "file": "Metadata/Terrain/EndGame/MapDefiledCathedral/Rooms/1x1/2_2.arm",
      "room_tag": ""
    },
    {
      "file": "Metadata/Terrain/EndGame/MapDefiledCathedral/Rooms/1x1/2_3.arm",
      "room_tag": ""
    },
    {
      "file": "Metadata/Terrain/EndGame/MapDefiledCathedral/Rooms/1x1/3_1.arm",
      "room_tag": ""
    },
    {
      "file": "Metadata/Terrain/EndGame/MapDefiledCathedral/Rooms/1x1/3_2.arm",
      "room_tag": ""
    },
    {
      "file": "Metadata/Terrain/EndGame/MapDefiledCathedral/Rooms/1x1/4_1.arm",
      "room_tag": ""
    },
    {
      "file": "Metadata/Terrain/EndGame/MapDefiledCathedral/Rooms/2x2/defiled_stained_straight_01.arm",
      "prefix": [
        "100"
      ],
      "room_tag": ""
    },
    {
      "file": "Metadata/Terrain/EndGame/MapDefiledCathedral/Rooms/2x2/defiled_stained_straight_02.arm",
      "prefix": [
        "100"
      ],
      "room_tag": ""
    },
    {
      "file": "Metadata/Terrain/EndGame/MapDefiledCathedral/Rooms/2x2/defiled_stained_straight_03.arm",
      "prefix": [
        "100"
      ],
      "room_tag": ""
    },
    {
      "file": "Metadata/Terrain/EndGame/MapDefiledCathedral/Rooms/2x2/defiled_stained_straight_04.arm",
      "prefix": [
        "100"
      ],
      "room_tag": ""
    },
    {
      "file": "Metadata/Terrain/EndGame/MapDefiledCathedral/Rooms/2x2/defiled_stained_straight_05.arm",
      "prefix": [
        "100"
      ],
      "room_tag": ""
    },
    {
      "file": "Metadata/Terrain/EndGame/MapDefiledCathedral/Rooms/2x2/defiled_stained_straight_06.arm",
      "prefix": [
        "100"
      ],
      "room_tag": ""
    },
    {
      "file": "Metadata/Terrain/EndGame/MapDefiledCathedral/Rooms/2x2/defiled_stained_straight_07.arm",
      "prefix": [
        "100"
      ],
      "room_tag": ""
    },
    {
      "file": "Metadata/Terrain/EndGame/MapDefiledCathedral/Rooms/2x2/defiled_stained_straight_08.arm",
      "prefix": [
        "100"
      ],
      "room_tag": ""
    },
    {
      "file": "Metadata/Terrain/EndGame/MapDefiledCathedral/Rooms/2x2/defiled_8_01.arm",
      "prefix": [
        "1"
      ],
      "room_tag": ""
    }
  ],
  "size": [
    9,
    10
  ],
  "strings": [
    "",
    "",
    "Metadata/Terrain/Act5/Area5/GroundTypes/innocence_boss_ground.gt"
  ],
  "tile_set": [
    {
      "file": "Metadata/Terrain/Blank.tdt"
    },
    {
      "file": "Metadata/Terrain/forced_blank.tdt",
      "prefix": [
        "100"
      ]
    },
    {
      "file": "Metadata/Terrain/Missions/Tiles/Oriath_generic_mission_01_01.tdt"
    },
    {
      "file": "Metadata/Terrain/Missions/Tiles/Slave_Pens_mission_01_01.tdt"
    },
    {
      "file": "Metadata/Terrain/Theopolis/Innocence/Terrace/Innocence_stainglass_convex_v01_01.tdt"
    },
    {
      "file": "Metadata/Terrain/Theopolis/Innocence/Feature/Innocence_boss_exit_v01_01.tdt"
    },
    {
      "file": "Metadata/Terrain/Theopolis/Innocence/Feature/Innocence_boss_transition_v01_01.tdt"
    },
    {
      "file": "Metadata/Terrain/Theopolis/Innocence/Feature/Innocence_floorfill_pulpit_putout.tdt"
    },
    {
      "file": "Metadata/Terrain/Theopolis/Innocence/Feature/Innocence_side_transition_v02_01.tdt"
    },
    {
      "file": "Metadata/Terrain/Theopolis/Innocence/Feature/Innocence_stainglass_boss_concave_shattered_v01_01.tdt"
    },
    {
      "file": "Metadata/Terrain/Theopolis/Innocence/Feature/Innocence_stainglass_boss_straight_v01_01.tdt"
    },
    {
      "file": "Metadata/Terrain/Theopolis/Innocence/Feature/Innocence_stainglass_boss_straight_v01_02.tdt"
    },
    {
      "file": "Metadata/Terrain/Theopolis/Innocence/Feature/transition_chamber_to_boss_shattered_v01_01.tdt"
    },
    {
      "file": "Metadata/Terrain/Theopolis/Innocence/Feature/transition_chamber_to_courts_shattered_v01_01.tdt"
    },
    {
      "file": "Metadata/Terrain/Theopolis/Innocence/Feature/Innocence_single_pillar1.tdt"
    },
    {
      "file": "Metadata/Terrain/Theopolis/Innocence/Floor/ChamberofInnocence_Illustration_v01_01.tdt",
      "suffix": [
        "I"
      ]
    },
    {
      "file": "Metadata/Terrain/Theopolis/Innocence/Floor/ChamberofInnocence_Illustration_v01_01.tdt",
      "suffix": [
        "R90"
      ]
    },
    {
      "file": "Metadata/Terrain/Theopolis/Innocence/Floor/ChamberofInnocence_floor_big_corner_v01_01.tdt"
    },
    {
      "file": "Metadata/Terrain/Theopolis/Innocence/Floor/ChamberofInnocence_floor_big_straight_v01_01.tdt"
    },
    {
      "file": "Metadata/Terrain/Theopolis/Innocence/Floor/ChamberofInnocence_floor_center_v01_01.tdt"
    },
    {
      "file": "Metadata/Terrain/Theopolis/Innocence/Floor/ChamberofInnocence_floor_circle_v01_01.tdt"
    },
    {
      "file": "Metadata/Terrain/Theopolis/Innocence/Floor/ChamberofInnocence_floor_corner_v01_01.tdt"
    },
    {
      "file": "Metadata/Terrain/Theopolis/Innocence/Floor/ChamberofInnocence_floor_straight_v01_01.tdt"
    },
    {
      "file": "Metadata/Terrain/Theopolis/Innocence/Floor/ChamberofInnocence_floor_v05_01.tdt"
    },
    {
      "file": "Metadata/Terrain/Theopolis/Innocence/Floor/ChamberofInnocence_floor_widecorner_v01_01.tdt"
    },
    {
      "file": "Metadata/Terrain/Theopolis/Innocence/Floor/ChamberofInnocence_floor_widecorner_v02_01.tdt"
    },
    {
      "file": "Metadata/Terrain/Theopolis/Innocence/Floor/Innocence_floor_putout_v02_01.tdt"
    },
    {
      "file": "Metadata/Terrain/Theopolis/Innocence/Floor/Innocence_floor_putout_v02_02.tdt"
    },
    {
      "file": "Metadata/Terrain/Theopolis/Innocence/Floor/Innocence_floor_relief_big_v01_01.tdt"
    },
    {
      "file": "Metadata/Terrain/Theopolis/Innocence/Floor/Innocence_floor_relief_putout_big_v01_01.tdt"
    },
    {
      "file": "Metadata/Terrain/Theopolis/Innocence/Floor/Innocence_floor_relief_putout_v01_01.tdt"
    },
    {
      "file": "Metadata/Terrain/Theopolis/Innocence/Floor/Innocence_floor_relief_putout_v01_02.tdt"
    },
    {
      "file": "Metadata/Terrain/Theopolis/Innocence/Floor/Innocence_floor_relief_v01_01.tdt"
    },
    {
      "file": "Metadata/Terrain/Theopolis/Innocence/Floor/Innocence_floor_relief_v01_02.tdt"
    },
    {
      "file": "Metadata/Terrain/Theopolis/Innocence/Floor/Innocence_floor_relief_v01_03.tdt"
    },
    {
      "file": "Metadata/Terrain/Theopolis/Innocence/Floor/Innocence_floor_relief_v01_04.tdt"
    },
    {
      "file": "Metadata/Terrain/Theopolis/Innocence/Floor/Innocence_floor_v02_01.tdt"
    },
    {
      "file": "Metadata/Terrain/Theopolis/Innocence/Floor/Innocence_floor_v02_02.tdt"
    },
    {
      "file": "Metadata/Terrain/Theopolis/Innocence/Floor/Innocence_giant_pillar_putout_v01_01.tdt"
    },
    {
      "file": "Metadata/Terrain/Theopolis/Innocence/Floor/Innocence_giant_pillar_putout_v01_02.tdt"
    },
    {
      "file": "Metadata/Terrain/Theopolis/Innocence/Floor/Innocence_giant_pillar_v01_01.tdt"
    },
    {
      "file": "Metadata/Terrain/Theopolis/Innocence/Floor/Innocence_giant_pillar_v01_02.tdt"
    },
    {
      "file": "Metadata/Terrain/Theopolis/Innocence/Ledge/Innocence_ledge_concave_v01_01.tdt"
    },
    {
      "file": "Metadata/Terrain/Theopolis/Innocence/Ledge/Innocence_ledge_convex_v01_01.tdt"
    },
    {
      "file": "Metadata/Terrain/Theopolis/Innocence/Ledge/Innocence_ledge_curvedstairs_v01_01.tdt"
    },
    {
      "file": "Metadata/Terrain/Theopolis/Innocence/Ledge/Innocence_ledge_putout_curvedstairs_v01_01.tdt"
    },
    {
      "file": "Metadata/Terrain/Theopolis/Innocence/Ledge/Innocence_ledge_putout_stairs_v01_01.tdt"
    },
    {
      "file": "Metadata/Terrain/Theopolis/Innocence/Ledge/Innocence_ledge_stairs_v01_01.tdt"
    },
    {
      "file": "Metadata/Terrain/Theopolis/Innocence/Ledge/Innocence_ledge_straight_v01_01.tdt"
    },
    {
      "file": "Metadata/Terrain/Theopolis/Innocence/Ledge/Innocence_ledge_thickwallheightconvex_putout_v02_01.tdt"
    },
    {
      "file": "Metadata/Terrain/Theopolis/Innocence/Ledge/Innocence_ledge_thickwallheightconvex_v01_01.tdt"
    },
    {
      "file": "Metadata/Terrain/Theopolis/Innocence/Ledge/Innocence_ledge_to_putout_stairs_v01_01.tdt"
    },
    {
      "file": "Metadata/Terrain/Theopolis/Innocence/Ledge/Innocence_ledge_to_stairs_v01_01.tdt"
    },
    {
      "file": "Metadata/Terrain/Theopolis/Innocence/Ledge/Innocence_ledge_to_thickwall_quad_v01_01.tdt"
    },
    {
      "file": "Metadata/Terrain/Theopolis/Innocence/Ledge/Innocence_ledge_to_thickwall_straight_v01_01.tdt"
    },
    {
      "file": "Metadata/Terrain/Theopolis/Innocence/Stairs/Innocence_stairs_concave_v01_01.tdt"
    },
    {
      "file": "Metadata/Terrain/Theopolis/Innocence/Stairs/Innocence_stairs_convex_v01_01.tdt"
    },
    {
      "file": "Metadata/Terrain/Theopolis/Innocence/Stairs/Innocence_stairs_putout_concave_v01_01.tdt"
    },
    {
      "file": "Metadata/Terrain/Theopolis/Innocence/Stairs/Innocence_stairs_putout_convex_v01_01.tdt"
    },
    {
      "file": "Metadata/Terrain/Theopolis/Innocence/Stairs/Innocence_stairs_putout_straight_v01_02.tdt"
    },
    {
      "file": "Metadata/Terrain/Theopolis/Innocence/Stairs/Innocence_stairs_straight_v01_01.tdt"
    },
    {
      "file": "Metadata/Terrain/Theopolis/Innocence/Stairs/Innocence_stairs_straight_v01_02.tdt"
    },
    {
      "file": "Metadata/Terrain/Theopolis/Innocence/Terrace/Innocence_brokenstainedglass_to_terrace_v01_01.tdt"
    },
    {
      "file": "Metadata/Terrain/Theopolis/Innocence/Terrace/Innocence_doubleledge_concave_v01_01.tdt"
    },
    {
      "file": "Metadata/Terrain/Theopolis/Innocence/Terrace/Innocence_doubleledge_convex_v01_01.tdt"
    },
    {
      "file": "Metadata/Terrain/Theopolis/Innocence/Terrace/Innocence_doubleledge_stairs_putout_v01_01.tdt"
    },
    {
      "file": "Metadata/Terrain/Theopolis/Innocence/Terrace/Innocence_doubleledge_stairs_putout_v02_01.tdt"
    },
    {
      "file": "Metadata/Terrain/Theopolis/Innocence/Terrace/Innocence_doubleledge_stairs_v01_01.tdt"
    },
    {
      "file": "Metadata/Terrain/Theopolis/Innocence/Terrace/Innocence_doubleledge_stairs_v02_01.tdt"
    },
    {
      "file": "Metadata/Terrain/Theopolis/Innocence/Terrace/Innocence_stainglass_boss_concave_shattered_v02_01.tdt"
    },
    {
      "file": "Metadata/Terrain/Theopolis/Innocence/Terrace/Innocence_stainglass_boss_straight_shattered_v02_01.tdt"
    },
    {
      "file": "Metadata/Terrain/Theopolis/Innocence/Terrace/Innocence_stainglass_concave_shattered_v01_01.tdt",
      "suffix": [
        "I"
      ]
    },
    {
      "file": "Metadata/Terrain/Theopolis/Innocence/Terrace/Innocence_stainglass_concave_shattered_v01_01.tdt",
      "suffix": [
        "R270"
      ]
    },
    {
      "file": "Metadata/Terrain/Theopolis/Innocence/Terrace/Innocence_stainglass_concave_shattered_novfx_v01_01.tdt",
      "suffix": [
        "R180"
      ]
    },
    {
      "file": "Metadata/Terrain/Theopolis/Innocence/Terrace/Innocence_stainglass_concave_shattered_novfx_v01_01.tdt",
      "suffix": [
        "R90"
      ]
    },
    {
      "file": "Metadata/Terrain/Theopolis/Innocence/Terrace/Innocence_stainglass_concave_to_thickwall_shattered_v01_01.tdt"
    },
    {
      "file": "Metadata/Terrain/Theopolis/Innocence/Terrace/Innocence_stainglass_convex_shattered_v01_01.tdt"
    },
    {
      "file": "Metadata/Terrain/Theopolis/Innocence/Terrace/Innocence_stainglass_convex_to_thickwall_v01_01.tdt"
    },
    {
      "file": "Metadata/Terrain/Theopolis/Innocence/Terrace/Innocence_stainglass_straight_shattered_v02_01.tdt"
    },
    {
      "file": "Metadata/Terrain/Theopolis/Innocence/Terrace/Innocence_stainglass_straight_shattered_v03_01.tdt"
    },
    {
      "file": "Metadata/Terrain/Theopolis/Innocence/Terrace/Innocence_stainglass_straight_shattered_v03_02.tdt"
    },
    {
      "file": "Metadata/Terrain/Theopolis/Innocence/Terrace/Innocence_stainglass_straight_to_thickwall_v01_01.tdt"
    },
    {
      "file": "Metadata/Terrain/Theopolis/Innocence/Terrace/Innocence_stainglass_straight_to_thickwall_v02_01.tdt"
    },
    {
      "file": "Metadata/Terrain/Theopolis/Innocence/Terrace/Innocence_stainglass_straight_v02_02.tdt"
    },
    {
      "file": "Metadata/Terrain/Theopolis/Innocence/Terrace/Innocence_terrace_concave_v01_01.tdt"
    },
    {
      "file": "Metadata/Terrain/Theopolis/Innocence/Terrace/Innocence_terrace_convex_v01_01.tdt"
    },
    {
      "file": "Metadata/Terrain/Theopolis/Innocence/Terrace/Innocence_terrace_edge_both_thinwall_v01_01.tdt"
    },
    {
      "file": "Metadata/Terrain/Theopolis/Innocence/Terrace/Innocence_terrace_edge_bottom_thinwall_v01_01.tdt"
    },
    {
      "file": "Metadata/Terrain/Theopolis/Innocence/Terrace/Innocence_terrace_edge_concave_v01_01.tdt"
    },
    {
      "file": "Metadata/Terrain/Theopolis/Innocence/Terrace/Innocence_terrace_edge_convex_v01_01.tdt"
    },
    {
      "file": "Metadata/Terrain/Theopolis/Innocence/Terrace/Innocence_terrace_edge_putout_both_thinwall_v01_01.tdt"
    },
    {
      "file": "Metadata/Terrain/Theopolis/Innocence/Terrace/Innocence_terrace_edge_putout_bottom_thinwall_v01_01.tdt"
    },
    {
      "file": "Metadata/Terrain/Theopolis/Innocence/Terrace/Innocence_terrace_edge_putout_concave_v01_01.tdt"
    },
    {
      "file": "Metadata/Terrain/Theopolis/Innocence/Terrace/Innocence_terrace_edge_putout_convex_v01_01.tdt"
    },
    {
      "file": "Metadata/Terrain/Theopolis/Innocence/Terrace/Innocence_terrace_edge_putout_straight_v01_01.tdt"
    },
    {
      "file": "Metadata/Terrain/Theopolis/Innocence/Terrace/Innocence_terrace_edge_putout_top_thinwall_v01_01.tdt"
    },
    {
      "file": "Metadata/Terrain/Theopolis/Innocence/Terrace/Innocence_terrace_edge_straight_v01_01.tdt"
    },
    {
      "file": "Metadata/Terrain/Theopolis/Innocence/Terrace/Innocence_terrace_edge_top_thinwall_v01_01.tdt"
    },
    {
      "file": "Metadata/Terrain/Theopolis/Innocence/Terrace/Innocence_terrace_stairs_convex_v01_01.tdt"
    },
    {
      "file": "Metadata/Terrain/Theopolis/Innocence/Terrace/Innocence_terrace_stairs_putout_convex_v01_01.tdt"
    },
    {
      "file": "Metadata/Terrain/Theopolis/Innocence/Terrace/Innocence_terrace_stairs_putout_convex_v01_02.tdt"
    },
    {
      "file": "Metadata/Terrain/Theopolis/Innocence/Terrace/Innocence_terrace_stairs_putout_convex_v01_03.tdt"
    },
    {
      "file": "Metadata/Terrain/Theopolis/Innocence/Terrace/Innocence_terrace_straight_shattered_v01_04.tdt"
    },
    {
      "file": "Metadata/Terrain/Theopolis/Innocence/Terrace/Innocence_terrace_straight_shattered_v01_05.tdt"
    },
    {
      "file": "Metadata/Terrain/Theopolis/Innocence/Terrace/Innocence_terrace_straight_shattered_v01_06.tdt"
    },
    {
      "file": "Metadata/Terrain/Theopolis/Innocence/Terrace/Innocence_terrace_to_thickwall_v01_01.tdt"
    },
    {
      "file": "Metadata/Terrain/Theopolis/Innocence/Terrace/Innocence_terrace_to_thickwall_v02_01.tdt"
    },
    {
      "file": "Metadata/Terrain/Theopolis/Innocence/Terrace/Innocence_terrace_to_thinwall_v01_01.tdt"
    },
    {
      "file": "Metadata/Terrain/Theopolis/Innocence/Terrace/Innocence_thickwall_to_stainedglasswall_v01_01.tdt"
    },
    {
      "file": "Metadata/Terrain/Theopolis/Innocence/Terrace/Innocence_thickwall_to_terrace_concave_v01_01.tdt"
    },
    {
      "file": "Metadata/Terrain/Theopolis/Innocence/ThickWall/Innocence_thickwall_concave_v01_01.tdt"
    },
    {
      "file": "Metadata/Terrain/Theopolis/Innocence/ThickWall/Innocence_thickwall_convex_v01_01.tdt"
    },
    {
      "file": "Metadata/Terrain/Theopolis/Innocence/ThickWall/Innocence_thickwall_putout_concave_v01_01.tdt"
    },
    {
      "file": "Metadata/Terrain/Theopolis/Innocence/ThickWall/Innocence_thickwall_putout_convex_v01_01.tdt"
    },
    {
      "file": "Metadata/Terrain/Theopolis/Innocence/ThickWall/Innocence_thickwall_putout_straight_feature.tdt"
    },
    {
      "file": "Metadata/Terrain/Theopolis/Innocence/ThickWall/Innocence_thickwall_putout_straight_v01_01.tdt"
    },
    {
      "file": "Metadata/Terrain/Theopolis/Innocence/ThickWall/Innocence_thickwall_straight_v01_01.tdt"
    },
    {
      "file": "Metadata/Terrain/Theopolis/Innocence/ThickWall/Innocence_thickwall_straight_v01_02.tdt"
    },
    {
      "file": "Metadata/Terrain/Theopolis/Innocence/ThickWall/Innocence_thickwall_straight_v01_03.tdt"
    },
    {
      "file": "Metadata/Terrain/Theopolis/Innocence/ThickWall/Innocence_thickwall_straight_v01_04.tdt"
    },
    {
      "file": "Metadata/Terrain/Theopolis/Innocence/ThickWall/Innocence_thickwall_straight_v01_05.tdt"
    },
    {
      "file": "Metadata/Terrain/Theopolis/Innocence/ThinWall/Innocence_thickwall_to_thinwall_corner_v01_01.tdt"
    },
    {
      "file": "Metadata/Terrain/Theopolis/Innocence/ThinWall/Innocence_thickwall_to_thinwall_putout_corner_v01_01.tdt"
    },
    {
      "file": "Metadata/Terrain/Theopolis/Innocence/ThinWall/Innocence_thickwall_to_thinwall_putout_straight_v01_01.tdt"
    },
    {
      "file": "Metadata/Terrain/Theopolis/Innocence/ThinWall/Innocence_thickwall_to_thinwall_straight_v01_01.tdt"
    },
    {
      "file": "Metadata/Terrain/Theopolis/Innocence/ThinWall/Innocence_thinwall_3way_v01_01.tdt"
    },
    {
      "file": "Metadata/Terrain/Theopolis/Innocence/ThinWall/Innocence_thinwall_corner_v01_01.tdt"
    },
    {
      "file": "Metadata/Terrain/Theopolis/Innocence/ThinWall/Innocence_thinwall_cross_door_v01_01.tdt"
    },
    {
      "file": "Metadata/Terrain/Theopolis/Innocence/ThinWall/Innocence_thinwall_cross_v01_01.tdt"
    },
    {
      "file": "Metadata/Terrain/Theopolis/Innocence/ThinWall/Innocence_thinwall_door_corner_v01_01.tdt"
    },
    {
      "file": "Metadata/Terrain/Theopolis/Innocence/ThinWall/Innocence_thinwall_door_straight_v01_01.tdt"
    },
    {
      "file": "Metadata/Terrain/Theopolis/Innocence/ThinWall/Innocence_thinwall_putout_3way_v01_01.tdt"
    },
    {
      "file": "Metadata/Terrain/Theopolis/Innocence/ThinWall/Innocence_thinwall_putout_corner_v01_01.tdt"
    },
    {
      "file": "Metadata/Terrain/Theopolis/Innocence/ThinWall/Innocence_thinwall_putout_cross_door_v01_01.tdt"
    },
    {
      "file": "Metadata/Terrain/Theopolis/Innocence/ThinWall/Innocence_thinwall_putout_cross_v01_01.tdt"
    },
    {
      "file": "Metadata/Terrain/Theopolis/Innocence/ThinWall/Innocence_thinwall_putout_door_corner_v01_01.tdt"
    },
    {
      "file": "Metadata/Terrain/Theopolis/Innocence/ThinWall/Innocence_thinwall_putout_door_straight_v01_01.tdt"
    },
    {
      "file": "Metadata/Terrain/Theopolis/Innocence/ThinWall/Innocence_thinwall_putout_straight_end_v01_01.tdt"
    },
    {
      "file": "Metadata/Terrain/Theopolis/Innocence/ThinWall/Innocence_thinwall_putout_straight_v01_01.tdt"
    },
    {
      "file": "Metadata/Terrain/Theopolis/Innocence/ThinWall/Innocence_thinwall_straight_end_v01_01.tdt"
    },
    {
      "file": "Metadata/Terrain/Theopolis/Innocence/ThinWall/Innocence_thinwall_straight_v01_01.tdt"
    },
    {
      "file": "Metadata/Terrain/Theopolis/OriathSquare/Rosettes/chitus_rosette_defaced_v03_05.tdt"
    },
    {
      "file": "Metadata/Terrain/Mountain/Arena/Colosseum/Feature/colosseum_trap_door_v01_01.tdt",
      "prefix": [
        "100"
      ]
    }
  ],
  "version": 19
}