{
  "data": {
    "Default%": [
      0,
      0,
      0
    ],
    "MasterFile": "Metadata/Terrain/Act8/Area6/master.tsi"
  },
  "edge_count": 5,
  "edge_types": {
    "Metadata/Terrain/Dungeon/rooms.et": {
      "color": "#FF5A5A5A",
      "id": "rooms"
    }
  },
  "edges": [
    {
      "color": "#FF5A5A5A",
      "edge_type": "Metadata/Terrain/Dungeon/rooms.et",
      "from": 9,
      "path": [],
      "to": 3,
      "unknown": [
        100,
        0,
        "Metadata/Terrain/Dungeon/rooms.et",
        0,
        0,
        "",
        0,
        0,
        0,
        "P",
        "N",
        1
      ]
    },
    {
      "color": "#FF5A5A5A",
      "edge_type": "Metadata/Terrain/Dungeon/rooms.et",
      "from": 3,
      "path": [],
      "to": 8,
      "unknown": [
        100,
        0,
        "Metadata/Terrain/Dungeon/rooms.et",
        0,
        0,
        "",
        0,
        0,
        0,
        "P",
        "N",
        1
      ]
    },
    {
      "color": "#FF5A5A5A",
      "edge_type": "Metadata/Terrain/Dungeon/rooms.et",
      "from": 5,
      "path": [],
      "to": 6,
      "unknown": [
        100,
        0,
        "Metadata/Terrain/Dungeon/rooms.et",
        0,
        0,
        "",
        0,
        0,
        0,
        "P",
        "N",
        1
      ]
    },
    {
      "color": "#FF5A5A5A",
      "edge_type": "Metadata/Terrain/Dungeon/rooms.et",
      "from": 10,
      "path": [],
      "to": 2,
      "unknown": [
        100,
        0,
        "Metadata/Terrain/Dungeon/rooms.et",
        0,
        0,
        "",
        0,
        0,
        0,
        "P",
        "N",
        1
      ]
    },
    {
      "color": "#FF5A5A5A",
      "edge_type": "Metadata/Terrain/Dungeon/rooms.et",
      "from": 11,
      "path": [],
      "to": 0,
      "unknown": [
        100,
        0,
        "Metadata/Terrain/Dungeon/rooms.et",
        0,
        0,
        "",
        0,
        0,
        0,
        "P",
        "N",
        1
      ]
    }
  ],
  "fill_tiles": [
    {
      "file": "default"
    },
    {
      "file": "Metadata/Terrain/Blank.tdt",
      "prefix": [
        "100"
      ]
    },
    {
      "file": "BattlefieldTop"
    },
    {
      "file": "Metadata/Terrain/Blank.tdt",
      "prefix": [
        "200"
      ]
    },
    {
      "file": "IvoryTempleTrim"
    },
    {
      "file": "Metadata/Terrain/Blank.tdt",
      "prefix": [
        "200"
      ]
    },
    {
      "file": "CityInsideWall"
    },
    {
      "file": "Metadata/Terrain/RuinedCity/LargeWall/battlefield_wall_fill_01.tdt",
      "prefix": [
        "1"
      ]
    },
    {
      "file": "CityWater"
    },
    {
      "file": "Metadata/Terrain/RuinedCity/DockLedgeMosiac/battlefield_waterfill_01_01.tdt",
      "prefix": [
        "1"
      ]
    },
    {
      "file": "BlackInsideWall"
    },
    {
      "file": "Metadata/Terrain/RuinedCity/LargeWall/battlefield_wall_fill_01.tdt",
      "prefix": [
        "1"
      ]
    },
    {
      "file": "Metadata/Terrain/RuinedCity/LargeWall/battlefield_wall_fill_02.tdt",
      "prefix": [
        "1"
      ]
    },
    {
      "file": "CityPoolWater"
    },
    {
      "file": "Metadata/Terrain/RuinedCity/Stream/battlefield_shallowstream_fill_v01_01.tdt",
      "prefix": [
        "1"
      ]
    },
    {
      "file": "CityInsideGardenThickWall"
    },
    {
      "file": "Metadata/Terrain/RuinedCity/GardenThinWall/garden_thickwall_fill_v01_01.tdt",
      "prefix": [
        "1"
      ]
    }
  ],
  "master": {
    "ChestData": "chests.cht",
    "Doodads": "doodads.ddt",
    "EdgeCombination": "barracks.ecf",
    "EdgePoints": "Metadata/Terrain/edge_points.edp",
    "FillTiles": "random_fill_tiles.gft",
    "MaterialsList": "materials.mtd",
    "OuterBufferSize": null,
    "OuterGroundType": "Metadata/Terrain/black_inside_wall.gt",
    "OverrideSpawns": "Outdoor",
    "RoomOverlap": null,
    "RoomSet": "generate.rs",
    "RoomUnitSize": null,
    "StoreyHeight": null,
    "TileSet": "tiles.tst",
    "version": null
  },
  "node_count": 12,
  "nodes": [
    {
      "numbers": [
        4
      ],
      "room": "sewer",
      "strings": [
        "accessible",
        "killzone=8"
      ],
      "transform": "I",
      "unknown": [
        100,
        3,
        "N"
      ],
      "x": 32,
      "y": 59
    },
    {
      "numbers": [],
      "room": "templeentrance",
      "strings": [
        "entrance2",
        "killzone=4",
        "accessible"
      ],
      "transform": "I",
      "unknown": [
        100,
        15,
        "N"
      ],
      "x": 31,
      "y": 149
    },
    {
      "numbers": [
        3
      ],
      "room": "boss",
      "strings": [
        "accessible"
      ],
      "transform": "I",
      "unknown": [
        100,
        12,
        "N"
      ],
      "x": 32,
      "y": 122
    },
    {
      "numbers": [
        1,
        0
      ],
      "room": "stairsside",
      "strings": [
        "accessible"
      ],
      "transform": "I",
      "unknown": [
        100,
        9,
        "N"
      ],
      "x": 33,
      "y": 102
    },
    {
      "numbers": [],
      "room": "bridge",
      "strings": [
        "entrance3",
        "accessible"
      ],
      "transform": "I",
      "unknown": [
        100,
        0,
        "N"
      ],
      "x": 28,
      "y": 12
    },
    {
      "numbers": [
        2
      ],
      "room": "stairswaypoint",
      "strings": [
        "accessible"
      ],
      "transform": "I",
      "unknown": [
        100,
        6,
        "N"
      ],
      "x": 34,
      "y": 80
    },
    {
      "numbers": [
        2
      ],
      "room": "exit",
      "strings": [
        "accessible"
      ],
      "transform": "I",
      "unknown": [
        100,
        6,
        "N"
      ],
      "x": 78,
      "y": 81
    },
    {
      "numbers": [],
      "room": "wall",
      "strings": [
        "accessible"
      ],
      "transform": "I",
      "unknown": [
        100,
        15,
        "N"
      ],
      "x": 81,
      "y": 152
    },
    {
      "numbers": [
        1
      ],
      "room": "sidecellar",
      "strings": [
        "sidearea1",
        "unique1",
        "accessible"
      ],
      "transform": "I",
      "unknown": [
        100,
        9,
        "N"
      ],
      "x": 78,
      "y": 99
    },
    {
      "numbers": [
        0
      ],
      "room": "sidecellar2",
      "strings": [
        "sidearea1",
        "unique1",
        "accessible"
      ],
      "transform": "I",
      "unknown": [
        100,
        9,
        "N"
      ],
      "x": 10,
      "y": 103
    },
    {
      "numbers": [
        3
      ],
      "room": "sidecellar2",
      "strings": [
        "sidearea1",
        "unique1",
        "accessible"
      ],
      "transform": "I",
      "unknown": [
        100,
        12,
        "N"
      ],
      "x": 11,
      "y": 124
    },
    {
      "numbers": [
        4
      ],
      "room": "baths",
      "strings": [
        "default",
        "entrance1",
        "accessible"
      ],
      "transform": "FR90",
      "unknown": [
        100,
        3,
        "N"
      ],
      "x": 9,
      "y": 60
    }
  ],
  "room_set": [
    {
      "file": "Metadata/Shrines/city_01.arm",
      "room_tag": "shrine"
    },
    {
      "file": "Metadata/Terrain/Act8/Area6/Rooms/Fills/blank_fill.arm",
      "prefix": [
        "100"
      ],
      "room_tag": ""
    },
    {
      "file": "Metadata/Terrain/Act8/Area6/Rooms/Fills/black_fill.arm",
      "prefix": [
        "100"
      ],
      "room_tag": ""
    },
    {
      "file": "Metadata/Terrain/Act8/Area6/Rooms/Fills/garden_fill.arm",
      "prefix": [
        "100"
      ],
      "room_tag": ""
    },
    {
      "file": "Metadata/Terrain/Act8/Area6/Rooms/Fills/dock_fill.arm",
      "prefix": [
        "100"
      ],
      "room_tag": ""
    },
    {
      "file": "Metadata/Terrain/Act8/Area6/Rooms/Fills/wall_1.arm",
      "prefix": [
        "100"
      ],
      "room_tag": "wall"
    },
    {
      "file": "Metadata/Terrain/Act8/Area6/Rooms/LedgeStrip/straight_1.arm",
      "prefix": [
        "100"
      ],
      "room_tag": "stairsside"
    },
    {
      "file": "Metadata/Terrain/Act8/Area6/Rooms/LedgeStrip/straight_1_waypoint.arm",
      "prefix": [
        "100"
      ],
      "room_tag": "stairswaypoint"
    },
    {
      "file": "Metadata/Terrain/Act8/Area6/Rooms/LedgeStrip/straight_2_1.arm",
      "prefix": [
        "//!100"
      ],
      "room_tag": "stairs"
    },
    {
      "file": "Metadata/Terrain/Act8/Area6/Rooms/LedgeStrip/straight_2_1_waypoint.arm",
      "prefix": [
        "100"
      ],
      "room_tag": "stairswaypoint"
    },
    {
      "file": "Metadata/Terrain/Act8/Area6/Rooms/LedgeStrip/straight_2_2.arm",
      "prefix": [
        "100"
      ],
      "room_tag": "stairs"
    },
    {
      "file": "Metadata/Terrain/Act8/Area6/Rooms/Unique/side_cellar_entrance_1.arm",
      "prefix": [
        "100"
      ],
      "room_tag": "sidecellar"
    },
    {
      "file": "Metadata/Terrain/Act8/Area6/Rooms/Unique/side_cellar_entrance_2.arm",
      "prefix": [
        "100"
      ],
      "room_tag": "sidecellar2"
    },
    {
      "file": "Metadata/Terrain/Act8/Area6/Rooms/Unique/boss.arm",
      "prefix": [
        "100"
      ],
      "room_tag": "boss"
    },
    {
      "file": "Metadata/Terrain/Act8/Area6/Rooms/Unique/exit_1.arm",
      "prefix": [
        "100"
      ],
      "room_tag": "exit"
    },
    {
      "file": "Metadata/Terrain/Act8/Area6/Rooms/Unique/exit_2.arm",
      "prefix": [
        "100"
      ],
      "room_tag": "exit2"
    },
    {
      "file": "Metadata/Terrain/Act8/Area6/Rooms/Unique/temple_entrance_1_1.arm",
      "prefix": [
        "100"
      ],
      "room_tag": "templeentrance"
    },
    {
      "file": "Metadata/Terrain/Act8/Area6/Rooms/Unique/temple_entrance_1_2.arm",
      "prefix": [
        "100"
      ],
      "room_tag": "templeentrance"
    },
    {
      "file": "Metadata/Terrain/Act8/Area6/Rooms/Unique/temple_entrance_2_1.arm",
      "prefix": [
        "100"
      ],
      "room_tag": "templeentrance2"
    },
    {
      "file": "Metadata/Terrain/Act8/Area6/Rooms/Unique/temple_entrance_2_2.arm",
      "prefix": [
        "100"
      ],
      "room_tag": "templeentrance2"
    },
    {
      "file": "Metadata/Terrain/Act8/Area6/Rooms/Unique/bridge_1.arm",
      "prefix": [
        "100"
      ],
      "room_tag": "bridge"
    },
    {
      "file": "Metadata/Terrain/Act8/Area6/Rooms/Unique/sewer_entrance_1.arm",
      "prefix": [
        "100"
      ],
      "room_tag": "sewer"
    },
    {
      "file": "Metadata/Terrain/Act8/Area6/Rooms/Unique/sewer_entrance_3.arm",
      "prefix": [
        "100"
      ],
      "room_tag": "sewer"
    },
    {
      "file": "Metadata/Terrain/Act8/Area6/Rooms/Unique/baths_entrance.arm",
      "prefix": [
        "100"
      ],
      "room_tag": "baths"
    }
  ],
  "size": [
    4,
    9
  ],
  "strings": [
    "Metadata/Terrain/Act3/Area13/GroundTypes/barracks_top.gt",
    "Metadata/Terrain/Act3/Area13/GroundTypes/city_ground.gt",
    ""
  ],
  "tile_set": [
    {
      "file": "Metadata/Terrain/Blank.tdt",
      "prefix": [
        "100"
      ]
    },
    {
      "file": "Metadata/Terrain/forced_blank.tdt",
      "prefix": [
        "100"
      ]
    },
    {
      "file": "Metadata/Terrain/Missions/Tiles/catacombs_entrance_transition_v01_01.tdt"
    },
    {
      "file": "Metadata/Terrain/Missions/Tiles/jail_entrance_01_01.tdt"
    },
    {
      "file": "Metadata/Terrain/Missions/Tiles/lunaris_stairs_mission_v01_01.tdt"
    },
    {
      "file": "Metadata/Terrain/Missions/Tiles/slum_sewer_entrance_v04_01.tdt"
    },
    {
      "file": "Metadata/Terrain/Missions/Tiles/solaris_stairs_mission_v01_01.tdt"
    },
    {
      "file": "Metadata/Terrain/Missions/Tiles/templeruinforest_stairs_mission_v01_01.tdt"
    },
    {
      "file": "Metadata/Terrain/Missions/Tiles/warehouse_entrance_01_01.tdt"
    },
    {
      "file": "Metadata/Terrain/StoneCircles/stonecircle_story_06.tdt",
      "suffix": [
        "R90"
      ]
    },
    {
      "file": "Metadata/Terrain/RuinedCity/AreaTransitions/act3_prison_entrance_01_01.tdt"
    },
    {
      "file": "Metadata/Terrain/RuinedCity/AreaTransitions_Part2/EbonyBarracks_arch_v01_01.tdt"
    },
    {
      "file": "Metadata/Terrain/RuinedCity/AreaTransitions_Part2/act3_riverbridge_transition_v01_01_barracks.tdt"
    },
    {
      "file": "Metadata/Terrain/RuinedCity/AreaTransitions_Part2/act3_temple_entrance_v01_01.tdt"
    },
    {
      "file": "Metadata/Terrain/RuinedCity/AreaTransitions_Part2/battlefield_to_sewer_stairs_blocked_v01_01.tdt"
    },
    {
      "file": "Metadata/Terrain/RuinedCity/Bridge/riverbridge_corner_v01_02.tdt"
    },
    {
      "file": "Metadata/Terrain/RuinedCity/Bridge/riverbridge_shortstraight_v01_01.tdt"
    },
    {
      "file": "Metadata/Terrain/RuinedCity/Bridge/riverbridge_step_broken_v01_01.tdt"
    },
    {
      "file": "Metadata/Terrain/RuinedCity/Bridge/riverbridge_step_nostatue_v01_01.tdt"
    },
    {
      "file": "Metadata/Terrain/RuinedCity/Bridge/riverbridge_step_statue_v01_01.tdt"
    },
    {
      "file": "Metadata/Terrain/RuinedCity/DockLedgeGarden/garden_thickwall_wateredge_v01_01.tdt"
    },
    {
      "file": "Metadata/Terrain/RuinedCity/DockLedgeGarden/garden_thickwall_wateredge_v02_01.tdt"
    },
    {
      "file": "Metadata/Terrain/RuinedCity/Features/BodyPiles/act3_corpsepile_sml_v02_01.tdt"
    },
    {
      "file": "Metadata/Terrain/RuinedCity/Features/BodyPiles/act3_corpsepile_sml_v02_02.tdt"
    },
    {
      "file": "Metadata/Terrain/RuinedCity/Features/Garden/barracks_garden_treefence_v01_01.tdt"
    },
    {
      "file": "Metadata/Terrain/RuinedCity/Features/Garden/barracks_garden_treefence_v01_02.tdt"
    },
    {
      "file": "Metadata/Terrain/RuinedCity/Features/Garden/barracks_garden_treefence_v01_03.tdt"
    },
    {
      "file": "Metadata/Terrain/RuinedCity/Features/citywaypoint_v01_02.tdt"
    },
    {
      "file": "Metadata/Terrain/RuinedCity/GardenWalkway/Garden_walkway_thin_wall_L_ledge_v01_01.tdt"
    },
    {
      "file": "Metadata/Terrain/RuinedCity/GardenWalkway/Garden_walkway_thin_wall_L_ledge_v02_02.tdt"
    },
    {
      "file": "Metadata/Terrain/RuinedCity/GardenWalkway/Garden_walkway_thin_wall_L_v01_01.tdt"
    },
    {
      "file": "Metadata/Terrain/RuinedCity/GardenWalkway/Garden_walkway_thin_wall_L_v02_01.tdt"
    },
    {
      "file": "Metadata/Terrain/RuinedCity/GardenWalkway/Garden_walkway_thin_wall_ledge_v01_02.tdt"
    },
    {
      "file": "Metadata/Terrain/RuinedCity/GardenWalkway/Garden_walkway_thin_wall_v01_01.tdt"
    },
    {
      "file": "Metadata/Terrain/RuinedCity/GardenWalkway/Garden_walkway_wall_connection_v01_01_FAKE.tdt"
    },
    {
      "file": "Metadata/Terrain/RuinedCity/GardenWalkway/Garden_walkway_wall_water_connection_v01_01.tdt"
    },
    {
      "file": "Metadata/Terrain/RuinedCity/GardenWalkway/Garden_walkway_wall_water_special_v01_01.tdt"
    },
    {
      "file": "Metadata/Terrain/RuinedCity/IvoryTemple/LunarisWater/Act3_templetrim_goldpillar_01_01.tdt"
    },
    {
      "file": "Metadata/Terrain/RuinedCity/IvoryTemple/LunarisWater/Act3_templetrim_goldpillar_01_02.tdt"
    },
    {
      "file": "Metadata/Terrain/RuinedCity/IvoryTemple/LunarisWater/Act3_templetrim_goldpillar_01_03.tdt"
    },
    {
      "file": "Metadata/Terrain/RuinedCity/IvoryTemple/LunarisWater/Act3_templetrim_goldpillar_02_01.tdt"
    },
    {
      "file": "Metadata/Terrain/RuinedCity/IvoryTemple/LunarisWater/Act3_templetrim_goldpillar_03_01.tdt"
    },
    {
      "file": "Metadata/Terrain/RuinedCity/IvoryTemple/LunarisWater/Act3_templetrim_goldpillar_03_02.tdt"
    },
    {
      "file": "Metadata/Terrain/RuinedCity/IvoryTemple/LunarisWater/Garden_walkway_ivorytemple_v01_01.tdt"
    },
    {
      "file": "Metadata/Terrain/RuinedCity/IvoryTemple/LunarisWater/act3_temple_wall_concave_v01_01.tdt"
    },
    {
      "file": "Metadata/Terrain/RuinedCity/IvoryTemple/LunarisWater/act3_temple_wall_convex_v01_01.tdt"
    },
    {
      "file": "Metadata/Terrain/RuinedCity/IvoryTemple/LunarisWater/act3_temple_wall_straight_v01_01.tdt"
    },
    {
      "file": "Metadata/Terrain/RuinedCity/IvoryTemple/LunarisWater/battlefield_wall_to_ivorytemple_v01_01.tdt"
    },
    {
      "file": "Metadata/Terrain/RuinedCity/IvoryTemple/LunarisWater/battlefield_wall_to_ivorytemple_v01_02.tdt"
    },
    {
      "file": "Metadata/Terrain/RuinedCity/LargeWall/battlefield_arch_v01_01.tdt"
    },
    {
      "file": "Metadata/Terrain/RuinedCity/LargeWall/battlefield_wall_concave_v01_01.tdt"
    },
    {
      "file": "Metadata/Terrain/RuinedCity/LargeWall/battlefield_wall_convex_v01_01.tdt"
    },
    {
      "file": "Metadata/Terrain/RuinedCity/LargeWall/battlefield_wall_straight_v01_01.tdt"
    },
    {
      "file": "Metadata/Terrain/RuinedCity/LargeWall/battlefield_wall_water_concave_v01_01.tdt"
    },
    {
      "file": "Metadata/Terrain/RuinedCity/LargeWall/battlefield_wall_water_connection_v01_01.tdt"
    },
    {
      "file": "Metadata/Terrain/RuinedCity/LargeWall/battlefield_wall_water_straight_v01_01.tdt"
    },
    {
      "file": "Metadata/Terrain/RuinedCity/LargeWall/battlefield_walltoledge_v01_01.tdt"
    },
    {
      "file": "Metadata/Terrain/RuinedCity/LargeWall/battlefield_walltoledge_v01_02.tdt"
    },
    {
      "file": "Metadata/Terrain/RuinedCity/LargeWall/battlefield_walltoledge_v01_03.tdt"
    },
    {
      "file": "Metadata/Terrain/RuinedCity/LargeWallGardens/garden_arch_v01_01.tdt"
    },
    {
      "file": "Metadata/Terrain/RuinedCity/LargeWallGardens/garden_wall_thickwall_straight_v01_01.tdt"
    },
    {
      "file": "Metadata/Terrain/RuinedCity/LedgeMosaic/battlefield_smallstairs_v01_01.tdt"
    },
    {
      "file": "Metadata/Terrain/RuinedCity/LedgeMosaic/battlefield_smallstairs_v01_02.tdt"
    },
    {
      "file": "Metadata/Terrain/RuinedCity/LedgeMosaic/battlefield_smallstairs_v01_03.tdt"
    },
    {
      "file": "Metadata/Terrain/RuinedCity/LedgeMosaic/mosaic_ledge_concave_v01_01.tdt"
    },
    {
      "file": "Metadata/Terrain/RuinedCity/LedgeMosaic/mosaic_ledge_convex_v01_01.tdt"
    },
    {
      "file": "Metadata/Terrain/RuinedCity/LedgeMosaic/mosaic_ledge_sidestairs_v01_01.tdt"
    },
    {
      "file": "Metadata/Terrain/RuinedCity/LedgeMosaic/mosaic_ledge_smallstairs_v01_02.tdt"
    },
    {
      "file": "Metadata/Terrain/RuinedCity/LedgeMosaic/mosaic_ledge_stairs_v02_01.tdt"
    },
    {
      "file": "Metadata/Terrain/RuinedCity/LedgeMosaic/mosaic_ledge_stairs_v03_01.tdt"
    },
    {
      "file": "Metadata/Terrain/RuinedCity/LedgeMosaic/mosaic_ledge_straight_v01_01.tdt"
    },
    {
      "file": "Metadata/Terrain/RuinedCity/LedgeMosaic/mosaic_ledge_straight_v01_01_SPECIAL.tdt"
    },
    {
      "file": "Metadata/Terrain/RuinedCity/LedgeMosaic/mosaic_mediumstairs_v01_01.tdt"
    },
    {
      "file": "Metadata/Terrain/RuinedCity/LedgeMosaic/mosaic_mediumstairs_v01_02.tdt"
    },
    {
      "file": "Metadata/Terrain/RuinedCity/Stream/battlefield_lowstream_end_v01_01.tdt"
    },
    {
      "file": "Metadata/Terrain/RuinedCity/Stream/battlefield_lowstream_straight_v01_01.tdt"
    },
    {
      "file": "Metadata/Terrain/RuinedCity/Stream/battlefield_lowstream_straight_v01_02.tdt"
    },
    {
      "file": "Metadata/Terrain/RuinedCity/Stream/battlefield_shallowstream_corner_v01_01.tdt"
    },
    {
      "file": "Metadata/Terrain/RuinedCity/Stream/battlefield_shallowstream_corner_v01_02.tdt"
    },
    {
      "file": "Metadata/Terrain/RuinedCity/Stream/battlefield_shallowstream_straight_v01_01.tdt"
    },
    {
      "file": "Metadata/Terrain/Temple/Floor/temple_carpet_end_01_01.tdt",
      "suffix": []
    },
    {
      "file": "Metadata/Terrain/Temple/Floor/temple_carpet_oneside_01_01.tdt"
    },
    {
      "file": "Metadata/Terrain/Temple/Floor/temple_carpet_oneside_01_07.tdt"
    },
    {
      "file": "Metadata/Terrain/Temple/Floor/temple_carpet_straight_01_01.tdt",
      "suffix": []
    },
    {
      "file": "Metadata/Terrain/RuinedCity/Features/Tents/tent_small_folded_v01_02.tdt",
      "prefix": [
        "20"
      ]
    },
    {
      "file": "Metadata/Terrain/RuinedCity/Features/Tents/tent_mid_square_v02_02.tdt",
      "prefix": [
        "50"
      ]
    },
    {
      "file": "Metadata/Terrain/RuinedCity/Features/Tents/tent_large_collapsed_v01_01.tdt",
      "prefix": [
        "100"
      ]
    },
    {
      "file": "Metadata/Terrain/RuinedCity/Features/Tents/tent_mid_round_v01_01.tdt",
      "prefix": [
        "100"
      ]
    },
    {
      "file": "Metadata/Terrain/RuinedCity/Features/Tents/tent_mid_round_v01_02.tdt",
      "prefix": [
        "100"
      ]
    },
    {
      "file": "Metadata/Terrain/RuinedCity/Features/Tents/tent_mid_square_v01_01.tdt",
      "prefix": [
        "100"
      ]
    },
    {
      "file": "Metadata/Terrain/RuinedCity/Features/Tents/tent_mid_square_v02_01.tdt",
      "prefix": [
        "100"
      ]
    },
    {
      "file": "Metadata/Terrain/RuinedCity/Features/Tents/tent_mid_square_v02_03.tdt",
      "prefix": [
        "100"
      ]
    },
    {
      "file": "Metadata/Terrain/RuinedCity/Features/Tents/tent_small_folded_v01_01.tdt",
      "prefix": [
        "100"
      ]
    },
    {
      "file": "Metadata/Terrain/RuinedCity/Features/Tents/tent_small_v01_01.tdt",
      "prefix": [
        "100"
      ]
    }
  ],
  "version": 19
}