{
  "data": {
    "Default%": [
      0,
      0,
      0
    ],
    "MasterFile": "Metadata/Terrain/Act9/Area3/master.tsi"
  },
  "edge_count": 23,
  "edge_types": {
    "LakeRockwallRooms": "LakeRockwallRooms #FFb2b4bd\nwildcard\nMetadata/Terrain/Mountain/DriedLake/RockWall/lake_inside_rockwall.gt\n0 3 1 0 0\n",
    "MountainCliffRooms": "MountainCliffRooms #FF787c8c\nwildcard\nMetadata/Terrain/Mountain/DriedLake/LargeCliffs/mountain_inside_cliff.gt\n0 3 0 0 0\n",
    "RockwallCliff": "RockwallCliff #FF787c8c\nMetadata/Terrain/Mountain/DriedLake/RockWall/lake_inside_rockwall.gt\nMetadata/Terrain/Mountain/DriedLake/LargeCliffs/mountain_inside_cliff.gt\n0 3 0 0 0\n"
  },
  "edges": [
    {
      "color": "#FF787c8c",
      "edge_type": "MountainCliffRooms",
      "from": 1,
      "path": [],
      "to": 0,
      "unknown": [
        100,
        0,
        "Metadata/Terrain/Mountain/DriedLake/Rooms/large_cliff_rooms.et",
        0,
        0,
        "",
        0,
        0,
        0,
        "I",
        "N",
        1
      ]
    },
    {
      "color": "#FF787c8c",
      "edge_type": "RockwallCliff",
      "from": 12,
      "path": [],
      "to": 1,
      "unknown": [
        100,
        0,
        "Metadata/Terrain/Mountain/DriedLake/Rooms/rockwall_cliff_rooms.et",
        0,
        0,
        "",
        0,
        0,
        0,
        "I",
        "N",
        1
      ]
    },
    {
      "color": "#FF787c8c",
      "edge_type": "RockwallCliff",
      "from": 7,
      "path": [],
      "to": 2,
      "unknown": [
        100,
        0,
        "Metadata/Terrain/Mountain/DriedLake/Rooms/rockwall_cliff_rooms.et",
        0,
        0,
        "",
        0,
        0,
        10,
        "I",
        "N",
        1
      ]
    },
    {
      "color": "#FFb2b4bd",
      "edge_type": "LakeRockwallRooms",
      "from": 3,
      "path": [],
      "to": 4,
      "unknown": [
        100,
        1,
        "Metadata/Terrain/Mountain/DriedLake/Rooms/lake_rockwall_rooms.et",
        0,
        0,
        "",
        0,
        0,
        0,
        "I",
        "N",
        1
      ]
    },
    {
      "color": "#FFb2b4bd",
      "edge_type": "LakeRockwallRooms",
      "from": 21,
      "path": [],
      "to": 0,
      "unknown": [
        100,
        1,
        "Metadata/Terrain/Mountain/DriedLake/Rooms/lake_rockwall_rooms.et",
        0,
        0,
        "",
        0,
        0,
        0,
        "P",
        "N",
        1
      ]
    },
    {
      "color": "#FFb2b4bd",
      "edge_type": "LakeRockwallRooms",
      "from": 20,
      "path": [],
      "to": 6,
      "unknown": [
        100,
        1,
        "Metadata/Terrain/Mountain/DriedLake/Rooms/lake_rockwall_rooms.et",
        0,
        0,
        "",
        0,
        0,
        0,
        "I",
        "N",
        1
      ]
    },
    {
      "color": "#FF787c8c",
      "edge_type": "RockwallCliff",
      "from": 15,
      "path": [],
      "to": 7,
      "unknown": [
        100,
        0,
        "Metadata/Terrain/Mountain/DriedLake/Rooms/rockwall_cliff_rooms.et",
        0,
        0,
        "",
        0,
        0,
        10,
        "I",
        "N",
        1
      ]
    },
    {
      "color": "#FFb2b4bd",
      "edge_type": "LakeRockwallRooms",
      "from": 14,
      "path": [],
      "to": 3,
      "unknown": [
        100,
        1,
        "Metadata/Terrain/Mountain/DriedLake/Rooms/lake_rockwall_rooms.et",
        0,
        0,
        "",
        0,
        0,
        0,
        "P",
        "N",
        1
      ]
    },
    {
      "color": "#FFb2b4bd",
      "edge_type": "LakeRockwallRooms",
      "from": 8,
      "path": [],
      "to": 10,
      "unknown": [
        100,
        0,
        "Metadata/Terrain/Mountain/DriedLake/Rooms/lake_rockwall_rooms.et",
        0,
        0,
        "",
        0,
        0,
        0,
        "P",
        "N",
        1
      ]
    },
    {
      "color": "#FFb2b4bd",
      "edge_type": "LakeRockwallRooms",
      "from": 8,
      "path": [],
      "to": 11,
      "unknown": [
        100,
        1,
        "Metadata/Terrain/Mountain/DriedLake/Rooms/lake_rockwall_rooms.et",
        0,
        0,
        "",
        0,
        0,
        0,
        "I",
        "N",
        1
      ]
    },
    {
      "color": "#FF787c8c",
      "edge_type": "RockwallCliff",
      "from": 2,
      "path": [],
      "to": 13,
      "unknown": [
        100,
        0,
        "Metadata/Terrain/Mountain/DriedLake/Rooms/rockwall_cliff_rooms.et",
        0,
        0,
        "",
        0,
        0,
        10,
        "I",
        "N",
        1
      ]
    },
    {
      "color": "#FF787c8c",
      "edge_type": "RockwallCliff",
      "from": 12,
      "path": [],
      "to": 11,
      "unknown": [
        100,
        1,
        "Metadata/Terrain/Mountain/DriedLake/Rooms/rockwall_cliff_rooms.et",
        0,
        0,
        "",
        0,
        0,
        0,
        "P",
        "N",
        1
      ]
    },
    {
      "color": "#FF787c8c",
      "edge_type": "RockwallCliff",
      "from": 9,
      "path": [],
      "to": 13,
      "unknown": [
        100,
        1,
        "Metadata/Terrain/Mountain/DriedLake/Rooms/rockwall_cliff_rooms.et",
        0,
        0,
        "",
        0,
        0,
        0,
        "P",
        "N",
        1
      ]
    },
    {
      "color": "#FF787c8c",
      "edge_type": "MountainCliffRooms",
      "from": 9,
      "path": [],
      "to": 5,
      "unknown": [
        100,
        0,
        "Metadata/Terrain/Mountain/DriedLake/Rooms/large_cliff_rooms.et",
        0,
        0,
        "",
        0,
        0,
        0,
        "P",
        "N",
        1
      ]
    },
    {
      "color": "#FF787c8c",
      "edge_type": "MountainCliffRooms",
      "from": 5,
      "path": [],
      "to": 11,
      "unknown": [
        100,
        0,
        "Metadata/Terrain/Mountain/DriedLake/Rooms/large_cliff_rooms.et",
        0,
        0,
        "",
        0,
        0,
        0,
        "P",
        "N",
        1
      ]
    },
    {
      "color": "#FFb2b4bd",
      "edge_type": "LakeRockwallRooms",
      "from": 9,
      "path": [],
      "to": 14,
      "unknown": [
        100,
        1,
        "Metadata/Terrain/Mountain/DriedLake/Rooms/lake_rockwall_rooms.et",
        0,
        0,
        "",
        0,
        0,
        0,
        "P",
        "N",
        1
      ]
    },
    {
      "color": "#FF787c8c",
      "edge_type": "RockwallCliff",
      "from": 0,
      "path": [],
      "to": 15,
      "unknown": [
        100,
        0,
        "Metadata/Terrain/Mountain/DriedLake/Rooms/rockwall_cliff_rooms.et",
        0,
        0,
        "",
        0,
        0,
        0,
        "I",
        "N",
        1
      ]
    },
    {
      "color": "#FFb2b4bd",
      "edge_type": "LakeRockwallRooms",
      "from": 19,
      "path": [],
      "to": 1,
      "unknown": [
        100,
        0,
        "Metadata/Terrain/Mountain/DriedLake/Rooms/lake_rockwall_rooms.et",
        0,
        0,
        "",
        0,
        0,
        0,
        "I",
        "N",
        1
      ]
    },
    {
      "color": "#FFb2b4bd",
      "edge_type": "LakeRockwallRooms",
      "from": 4,
      "path": [],
      "to": 17,
      "unknown": [
        100,
        1,
        "Metadata/Terrain/Mountain/DriedLake/Rooms/lake_rockwall_rooms.et",
        0,
        0,
        "",
        0,
        0,
        0,
        "I",
        "N",
        1
      ]
    },
    {
      "color": "#FFb2b4bd",
      "edge_type": "LakeRockwallRooms",
      "from": 10,
      "path": [],
      "to": 18,
      "unknown": [
        100,
        0,
        "Metadata/Terrain/Mountain/DriedLake/Rooms/lake_rockwall_rooms.et",
        0,
        0,
        "",
        0,
        0,
        0,
        "I",
        "N",
        1
      ]
    },
    {
      "color": "#FFb2b4bd",
      "edge_type": "LakeRockwallRooms",
      "from": 18,
      "path": [],
      "to": 19,
      "unknown": [
        100,
        0,
        "Metadata/Terrain/Mountain/DriedLake/Rooms/lake_rockwall_rooms.et",
        0,
        0,
        "",
        0,
        0,
        0,
        "I",
        "N",
        1
      ]
    },
    {
      "color": "#FFb2b4bd",
      "edge_type": "LakeRockwallRooms",
      "from": 17,
      "path": [],
      "to": 20,
      "unknown": [
        100,
        1,
        "Metadata/Terrain/Mountain/DriedLake/Rooms/lake_rockwall_rooms.et",
        0,
        0,
        "",
        0,
        0,
        0,
        "I",
        "N",
        1
      ]
    },
    {
      "color": "#FFb2b4bd",
      "edge_type": "LakeRockwallRooms",
      "from": 6,
      "path": [],
      "to": 21,
      "unknown": [
        100,
        1,
        "Metadata/Terrain/Mountain/DriedLake/Rooms/lake_rockwall_rooms.et",
        0,
        0,
        "",
        0,
        0,
        0,
        "P",
        "N",
        1
      ]
    }
  ],
  "master": {
    "ChestData": "chests.cht",
    "Critters": "critters.clt",
    "Decals": "decals.dct",
    "Doodads": "doodads.ddt",
    "EdgeCombination": "combo.ecf",
    "EnvironmentPreload": "9_3_event",
    "FillTiles": "random_fill_tiles.gft",
    "MaterialsList": "materials.mtd",
    "OuterBufferSize": null,
    "OuterGroundType": "Metadata/Terrain/Mountain/DriedLake/LargeCliffs/mountain_inside_cliff.gt",
    "OverrideSpawns": "Outdoor",
    "Reskin": "foothills",
    "RoomOverlap": null,
    "RoomSet": "generate.rs",
    "RoomUnitSize": null,
    "StoreyHeight": null,
    "TileSet": "tiles.tst",
    "version": null
  },
  "node_count": 22,
  "nodes": [
    {
      "numbers": [
        16,
        4,
        0
      ],
      "room": "entrance",
      "strings": [
        "default",
        "entrance1"
      ],
      "transform": "I",
      "unknown": [
        100,
        0,
        "N"
      ],
      "x": 35,
      "y": 221
    },
    {
      "numbers": [
        17,
        1,
        0
      ],
      "room": "connection",
      "strings": [],
      "transform": "FR90",
      "unknown": [
        100,
        0,
        "N"
      ],
      "x": 123,
      "y": 192
    },
    {
      "numbers": [
        2,
        10
      ],
      "room": "",
      "strings": [],
      "transform": "(any)",
      "unknown": [
        100,
        0,
        "N"
      ],
      "x": 311,
      "y": 13
    },
    {
      "numbers": [
        3,
        7
      ],
      "room": "entrance_oasis",
      "strings": [
        "entrance2"
      ],
      "transform": "I",
      "unknown": [
        100,
        0,
        "N"
      ],
      "x": 236,
      "y": 57
    },
    {
      "numbers": [
        3,
        18
      ],
      "room": "",
      "strings": [],
      "transform": "(any)",
      "unknown": [
        100,
        0,
        "N"
      ],
      "x": 198,
      "y": 32
    },
    {
      "numbers": [
        14,
        13
      ],
      "room": "exit",
      "strings": [
        "entrance3"
      ],
      "transform": "I",
      "unknown": [
        100,
        0,
        "N"
      ],
      "x": 214,
      "y": 195
    },
    {
      "numbers": [
        5,
        22
      ],
      "room": "sidearea",
      "strings": [
        "sidearea1",
        "unique1"
      ],
      "transform": "R90",
      "unknown": [
        100,
        0,
        "N"
      ],
      "x": 37,
      "y": 100
    },
    {
      "numbers": [
        2,
        6
      ],
      "room": "",
      "strings": [],
      "transform": "(any)",
      "unknown": [
        100,
        0,
        "N"
      ],
      "x": 14,
      "y": 12
    },
    {
      "numbers": [
        8,
        9
      ],
      "room": "mapboss",
      "strings": [],
      "transform": "R270",
      "unknown": [
        100,
        0,
        "N"
      ],
      "x": 142,
      "y": 123
    },
    {
      "numbers": [
        15,
        12,
        13
      ],
      "room": "connection",
      "strings": [],
      "transform": "FR90",
      "unknown": [
        100,
        0,
        "N"
      ],
      "x": 262,
      "y": 195
    },
    {
      "numbers": [
        8,
        19
      ],
      "room": "",
      "strings": [],
      "transform": "(any)",
      "unknown": [
        100,
        0,
        "N"
      ],
      "x": 142,
      "y": 101
    },
    {
      "numbers": [
        9,
        14,
        11
      ],
      "room": "connection",
      "strings": [],
      "transform": "R270",
      "unknown": [
        100,
        0,
        "N"
      ],
      "x": 195,
      "y": 194
    },
    {
      "numbers": [
        1,
        11
      ],
      "room": "",
      "strings": [],
      "transform": "(any)",
      "unknown": [
        100,
        0,
        "N"
      ],
      "x": 144,
      "y": 241
    },
    {
      "numbers": [
        10,
        12
      ],
      "room": "",
      "strings": [],
      "transform": "(any)",
      "unknown": [
        100,
        0,
        "N"
      ],
      "x": 313,
      "y": 192
    },
    {
      "numbers": [
        7,
        15
      ],
      "room": "",
      "strings": [],
      "transform": "(any)",
      "unknown": [
        100,
        0,
        "N"
      ],
      "x": 212,
      "y": 58
    },
    {
      "numbers": [
        6,
        16
      ],
      "room": "",
      "strings": [],
      "transform": "(any)",
      "unknown": [
        100,
        0,
        "N"
      ],
      "x": 9,
      "y": 129
    },
    {
      "numbers": [],
      "room": "waypoint",
      "strings": [],
      "transform": "I",
      "unknown": [
        100,
        0,
        "N"
      ],
      "x": 124,
      "y": 56
    },
    {
      "numbers": [
        18,
        21
      ],
      "room": "sidearea",
      "strings": [
        "sidearea1",
        "unique1"
      ],
      "transform": "R180",
      "unknown": [
        100,
        0,
        "N"
      ],
      "x": 53,
      "y": 35
    },
    {
      "numbers": [
        19,
        20
      ],
      "room": "",
      "strings": [],
      "transform": "(any)",
      "unknown": [
        100,
        0,
        "N"
      ],
      "x": 126,
      "y": 101
    },
    {
      "numbers": [
        20,
        17
      ],
      "room": "trailmarker",
      "strings": [],
      "transform": "R180",
      "unknown": [
        100,
        0,
        "N"
      ],
      "x": 125,
      "y": 125
    },
    {
      "numbers": [
        21,
        5
      ],
      "room": "",
      "strings": [],
      "transform": "(any)",
      "unknown": [
        100,
        0,
        "N"
      ],
      "x": 56,
      "y": 77
    },
    {
      "numbers": [
        22,
        4
      ],
      "room": "",
      "strings": [],
      "transform": "(any)",
      "unknown": [
        100,
        0,
        "N"
      ],
      "x": 36,
      "y": 144
    }
  ],
  "room_set": [],
  "size": [
    14,
    12
  ],
  "strings": [
    "Metadata/Terrain/Act4/Area2/GroundTypes/mountain_ground_top.gt",
    "Metadata/Terrain/Act4/Area2/GroundTypes/mountain_ground.gt",
    "Metadata/Terrain/Act4/Area2/GroundTypes/mountain_ground_bottom.gt"
  ],
  "tile_set": [
    {
      "file": "Metadata/Terrain/StoneCircles/stonecircle_story_06.tdt",
      "suffix": [
        "R90"
      ]
    }
  ],
  "version": 19
}