{
  "data": {
    "Default%": [
      0,
      0,
      0
    ],
    "MasterFile": "Metadata/Terrain/EndGame/MapCursus/master.tsi"
  },
  "edge_count": 14,
  "edge_types": {
    "CursusRidge": "CursusRidge #FF8bb67c\nwildcard\nwildcard\n0 1 0 0 0 1\n",
    "LakeRockwallRooms": "LakeRockwallRooms #FFb2b4bd\nwildcard\nMetadata/Terrain/Mountain/DriedLake/RockWall/lake_inside_rockwall.gt\n0 3 1 0 0\n",
    "void": "void #FF141414\nwildcard\nwildcard\n0 1 0\n"
  },
  "edges": [
    {
      "color": "#FFb2b4bd",
      "edge_type": "LakeRockwallRooms",
      "from": 0,
      "path": [],
      "to": 6,
      "unknown": [
        100,
        0,
        "Metadata/Terrain/Mountain/DriedLake/Rooms/lake_rockwall_rooms.et",
        0,
        0,
        "",
        0,
        0,
        0,
        "P",
        "N",
        1
      ]
    },
    {
      "color": "#FFb2b4bd",
      "edge_type": "LakeRockwallRooms",
      "from": 14,
      "path": [],
      "to": 1,
      "unknown": [
        100,
        0,
        "Metadata/Terrain/Mountain/DriedLake/Rooms/lake_rockwall_rooms.et",
        0,
        0,
        "",
        0,
        0,
        0,
        "P",
        "N",
        1
      ]
    },
    {
      "color": "#FF8bb67c",
      "edge_type": "CursusRidge",
      "from": 3,
      "path": [],
      "to": 11,
      "unknown": [
        100,
        0,
        "Metadata/Terrain/EndGame/MapCursus/Rooms/HeightChange/cursus_ridge.et",
        0,
        0,
        "",
        0,
        0,
        0,
        "P",
        "N",
        1
      ]
    },
    {
      "color": "#FFb2b4bd",
      "edge_type": "LakeRockwallRooms",
      "from": 13,
      "path": [],
      "to": 2,
      "unknown": [
        100,
        0,
        "Metadata/Terrain/Mountain/DriedLake/Rooms/lake_rockwall_rooms.et",
        0,
        100,
        "",
        0,
        0,
        0,
        "I",
        "N",
        1
      ]
    },
    {
      "color": "#FFb2b4bd",
      "edge_type": "LakeRockwallRooms",
      "from": 2,
      "path": [],
      "to": 0,
      "unknown": [
        100,
        0,
        "Metadata/Terrain/Mountain/DriedLake/Rooms/lake_rockwall_rooms.et",
        0,
        100,
        "",
        0,
        0,
        0,
        "I",
        "N",
        1
      ]
    },
    {
      "color": "#FF8bb67c",
      "edge_type": "CursusRidge",
      "from": 3,
      "path": [],
      "to": 7,
      "unknown": [
        100,
        0,
        "Metadata/Terrain/EndGame/MapCursus/Rooms/HeightChange/cursus_ridge.et",
        0,
        0,
        "",
        0,
        0,
        0,
        "P",
        "N",
        1
      ]
    },
    {
      "color": "#FF141414",
      "edge_type": "void",
      "from": 10,
      "path": [],
      "to": 9,
      "unknown": [
        100,
        0,
        "Metadata/Terrain/Tools/void.et",
        0,
        0,
        "",
        0,
        0,
        0,
        "P",
        "V",
        1
      ]
    },
    {
      "color": "#FF141414",
      "edge_type": "void",
      "from": 8,
      "path": [],
      "to": 10,
      "unknown": [
        100,
        0,
        "Metadata/Terrain/Tools/void.et",
        0,
        0,
        "",
        0,
        0,
        0,
        "P",
        "V",
        1
      ]
    },
    {
      "color": "#FFb2b4bd",
      "edge_type": "LakeRockwallRooms",
      "from": 1,
      "path": [],
      "to": 11,
      "unknown": [
        100,
        0,
        "Metadata/Terrain/Mountain/DriedLake/Rooms/lake_rockwall_rooms.et",
        0,
        100,
        "",
        0,
        0,
        0,
        "I",
        "N",
        1
      ]
    },
    {
      "color": "#FFb2b4bd",
      "edge_type": "LakeRockwallRooms",
      "from": 11,
      "path": [],
      "to": 5,
      "unknown": [
        100,
        0,
        "Metadata/Terrain/Mountain/DriedLake/Rooms/lake_rockwall_rooms.et",
        0,
        100,
        "",
        0,
        0,
        0,
        "I",
        "N",
        1
      ]
    },
    {
      "color": "#FF8bb67c",
      "edge_type": "CursusRidge",
      "from": 3,
      "path": [],
      "to": 12,
      "unknown": [
        100,
        0,
        "Metadata/Terrain/EndGame/MapCursus/Rooms/HeightChange/cursus_ridge.et",
        0,
        0,
        "",
        0,
        0,
        0,
        "P",
        "N",
        1
      ]
    },
    {
      "color": "#FFb2b4bd",
      "edge_type": "LakeRockwallRooms",
      "from": 15,
      "path": [],
      "to": 13,
      "unknown": [
        100,
        0,
        "Metadata/Terrain/Mountain/DriedLake/Rooms/lake_rockwall_rooms.et",
        0,
        100,
        "",
        0,
        0,
        0,
        "I",
        "N",
        1
      ]
    },
    {
      "color": "#FFb2b4bd",
      "edge_type": "LakeRockwallRooms",
      "from": 6,
      "path": [],
      "to": 14,
      "unknown": [
        100,
        0,
        "Metadata/Terrain/Mountain/DriedLake/Rooms/lake_rockwall_rooms.et",
        0,
        0,
        "",
        0,
        0,
        0,
        "P",
        "N",
        1
      ]
    },
    {
      "color": "#FFb2b4bd",
      "edge_type": "LakeRockwallRooms",
      "from": 5,
      "path": [],
      "to": 15,
      "unknown": [
        100,
        0,
        "Metadata/Terrain/Mountain/DriedLake/Rooms/lake_rockwall_rooms.et",
        0,
        100,
        "",
        0,
        0,
        0,
        "I",
        "N",
        1
      ]
    }
  ],
  "master": {
    "AllowChisel": null,
    "ChestData": "chests.cht",
    "Critters": "critters.clt",
    "Decals": "decals.dct",
    "Doodads": "doodads.ddt",
    "EdgeCombination": "combo.ecf",
    "FillTiles": "random_fill_tiles.gft",
    "MaterialsList": "materials.mtd",
    "OuterBufferSize": null,
    "OverrideSpawns": "Outdoor",
    "RoomOverlap": null,
    "RoomSet": "generate.rs",
    "RoomUnitSize": null,
    "StoreyHeight": null,
    "TileSet": "tiles.tst",
    "version": null
  },
  "node_count": 16,
  "nodes": [
    {
      "numbers": [
        0,
        4
      ],
      "room": "entrance",
      "strings": [
        "default",
        "unique1",
        "killzone=5"
      ],
      "transform": "I",
      "unknown": [
        100,
        0,
        "N"
      ],
      "x": 142,
      "y": 14
    },
    {
      "numbers": [
        1,
        8
      ],
      "room": "",
      "strings": [],
      "transform": "(any)",
      "unknown": [
        100,
        0,
        "N"
      ],
      "x": 122,
      "y": 123
    },
    {
      "numbers": [
        4,
        3
      ],
      "room": "entrance",
      "strings": [
        "default",
        "unique1",
        "killzone=5"
      ],
      "transform": "FI",
      "unknown": [
        100,
        0,
        "N"
      ],
      "x": 38,
      "y": 33
    },
    {
      "numbers": [
        10,
        5,
        2
      ],
      "room": "",
      "strings": [],
      "transform": "R180",
      "unknown": [
        100,
        0,
        "N"
      ],
      "x": 83,
      "y": 78
    },
    {
      "numbers": [],
      "room": "boss",
      "strings": [
        "telepad2",
        "teleport1-%areaname%"
      ],
      "transform": "I",
      "unknown": [
        100,
        0,
        "N"
      ],
      "x": 18,
      "y": 238
    },
    {
      "numbers": [
        13,
        9
      ],
      "room": "",
      "strings": [],
      "transform": "(any)",
      "unknown": [
        100,
        0,
        "N"
      ],
      "x": 29,
      "y": 123
    },
    {
      "numbers": [
        0,
        12
      ],
      "room": "",
      "strings": [],
      "transform": "(any)",
      "unknown": [
        100,
        0,
        "N"
      ],
      "x": 141,
      "y": 63
    },
    {
      "numbers": [
        5
      ],
      "room": "end",
      "strings": [],
      "transform": "FI",
      "unknown": [
        100,
        0,
        "N"
      ],
      "x": 122,
      "y": 62
    },
    {
      "numbers": [
        7
      ],
      "room": "",
      "strings": [],
      "transform": "(any)",
      "unknown": [
        100,
        0,
        "V"
      ],
      "x": 145,
      "y": 202
    },
    {
      "numbers": [
        6
      ],
      "room": "",
      "strings": [],
      "transform": "(any)",
      "unknown": [
        100,
        0,
        "V"
      ],
      "x": 149,
      "y": 145
    },
    {
      "numbers": [
        7,
        6
      ],
      "room": "",
      "strings": [],
      "transform": "(any)",
      "unknown": [
        100,
        0,
        "V"
      ],
      "x": 154,
      "y": 208
    },
    {
      "numbers": [
        9,
        2,
        8
      ],
      "room": "bossentry",
      "strings": [
        "telepad1",
        "teleport2-Arena",
        "killzone=0"
      ],
      "transform": "FI",
      "unknown": [
        100,
        0,
        "N"
      ],
      "x": 64,
      "y": 150
    },
    {
      "numbers": [
        10
      ],
      "room": "end",
      "strings": [],
      "transform": "I",
      "unknown": [
        100,
        0,
        "N"
      ],
      "x": 49,
      "y": 61
    },
    {
      "numbers": [
        3,
        11
      ],
      "room": "",
      "strings": [],
      "transform": "(any)",
      "unknown": [
        100,
        0,
        "N"
      ],
      "x": 33,
      "y": 56
    },
    {
      "numbers": [
        12,
        1
      ],
      "room": "sidelake",
      "strings": [
        "unique2",
        "sidearea"
      ],
      "transform": "R270",
      "unknown": [
        100,
        0,
        "N"
      ],
      "x": 128,
      "y": 104
    },
    {
      "numbers": [
        11,
        13
      ],
      "room": "sidelake",
      "strings": [
        "unique2",
        "sidearea"
      ],
      "transform": "R90",
      "unknown": [
        100,
        0,
        "N"
      ],
      "x": 16,
      "y": 100
    }
  ],
  "room_set": [],
  "size": [
    7,
    12
  ],
  "strings": [
    "",
    "",
    ""
  ],
  "tile_set": [
    {
      "file": "Metadata/Terrain/Mountain/DriedLake/AqueductNarrow/aqueduct_narrow_v01_02.tdt",
      "prefix": [
        "100"
      ],
      "suffix": [
        "R270"
      ]
    }
  ],
  "version": 19
}